stac_fastapi/mongo/__init__.py
stac_fastapi/mongo/app.py
stac_fastapi/mongo/config.py
stac_fastapi/mongo/database_logic.py
stac_fastapi/mongo/utilities.py
stac_fastapi.mongo-3.2.0.dist-info/LICENSE
stac_fastapi.mongo-3.2.0.dist-info/METADATA
stac_fastapi.mongo-3.2.0.dist-info/WHEEL
stac_fastapi.mongo-3.2.0.dist-info/entry_points.txt
stac_fastapi.mongo-3.2.0.dist-info/top_level.txt
stac_fastapi.mongo-3.2.0.dist-info/RECORD
