Metadata-Version: 2.1
Name: stac-fastapi.mongo
Version: 3.2.0
Summary: Mongodb stac-fastapi backend.
Home-page: https://github.com/Healy-Hyperspatial/stac-fastapi-mongo
License: MIT
Classifier: Intended Audience :: Developers
Classifier: Intended Audience :: Information Technology
Classifier: Intended Audience :: Science/Research
Classifier: Programming Language :: Python :: 3.8
Classifier: Programming Language :: Python :: 3.9
Classifier: Programming Language :: Python :: 3.10
Classifier: Programming Language :: Python :: 3.11
Classifier: License :: OSI Approved :: MIT License
Requires-Python: >=3.8
License-File: LICENSE
Requires-Dist: stac-fastapi.core ==2.4.0
Requires-Dist: motor ==3.3.2
Requires-Dist: pymongo ==4.6.2
Requires-Dist: uvicorn
Requires-Dist: starlette
Requires-Dist: typing-extensions ==4.4.0
Provides-Extra: dev
Requires-Dist: pytest ; extra == 'dev'
Requires-Dist: pytest-cov ; extra == 'dev'
Requires-Dist: pytest-asyncio ; extra == 'dev'
Requires-Dist: pre-commit ; extra == 'dev'
Requires-Dist: requests ; extra == 'dev'
Requires-Dist: ciso8601 ; extra == 'dev'
Requires-Dist: httpx ; extra == 'dev'
Provides-Extra: docs
Requires-Dist: mkdocs ; extra == 'docs'
Requires-Dist: mkdocs-material ; extra == 'docs'
Requires-Dist: pdocs ; extra == 'docs'
Provides-Extra: server
Requires-Dist: uvicorn[standard] ==0.19.0 ; extra == 'server'
